LICENSE
README.md
pyproject.toml
setup.py
src/py_gs1_barcode_engine/__init__.py
src/py_gs1_barcode_engine/py_gs1_barcode_engine.py
src/py_gs1_barcode_engine.egg-info/PKG-INFO
src/py_gs1_barcode_engine.egg-info/SOURCES.txt
src/py_gs1_barcode_engine.egg-info/dependency_links.txt
src/py_gs1_barcode_engine.egg-info/entry_points.txt
src/py_gs1_barcode_engine.egg-info/requires.txt
src/py_gs1_barcode_engine.egg-info/top_level.txt
src/py_gs1_barcode_engine/_pyinstaller/__init__.py
src/py_gs1_barcode_engine/_pyinstaller/hook-py_gs1_barcode_engine.py