Metadata-Version: 2.1
Name: py-gs1-barcode-engine
Version: 0.0.19
Summary: A thin Python wrapper of https://github.com/gs1/gs1-barcode-engine.
Home-page: https://bitbucket.org/stolmen/gs1-wrapper
Author: Edward Ong
Author-email: edward93@gmail.com
Requires-Python: >=3.6
License-File: LICENSE
